cagent/__init__.py
cagent/agent/__init__.py
cagent/agent/analyst.py
cagent/agent/artist.py
cagent/agent/blacksmith.py
cagent/agent/engineer.py
cagent/agent/professor.py
cagent/client/__init__.py
cagent/client/coingecko_client.py
cagent/client/fauna_client.py
cagent/client/node_client.py
cagent/client/openai_client.py
crypto_ai_agent-0.0.9.dist-info/LICENSE
crypto_ai_agent-0.0.9.dist-info/METADATA
crypto_ai_agent-0.0.9.dist-info/WHEEL
crypto_ai_agent-0.0.9.dist-info/top_level.txt
crypto_ai_agent-0.0.9.dist-info/RECORD
