Metadata-Version: 2.1
Name: crypto-ai-agent
Version: 0.0.9
Summary: Import your own Crypto AI Agent to help fetch, analyze, learn, understand and streamline your crypto work
Author: Voltfin Crypto
Author-email: zinnober.haus@gmail.com
Classifier: Programming Language :: Python :: 3
Classifier: License :: OSI Approved :: MIT License
Classifier: Operating System :: OS Independent
Requires-Python: >=3.9
License-File: LICENSE
